<PAMDataset>
  <Metadata>
    <MDI key="DataType">Generic</MDI>
  </Metadata>
  <Metadata domain="Esri">
    <MDI key="PyramidResamplingType">NEAREST</MDI>
  </Metadata>
  <PAMRasterBand band="1">
    <Histograms>
      <HistItem>
        <HistMin>-0.5</HistMin>
        <HistMax>131.5</HistMax>
        <BucketCount>132</BucketCount>
        <IncludeOutOfRange>1</IncludeOutOfRange>
        <Approximate>0</Approximate>
        <HistCounts>988277|0|0|0|0|0|0|0|0|0|0|0|0|0|0|0|0|0|0|0|0|0|0|0|0|0|0|0|0|0|0|0|0|0|0|0|0|0|0|0|0|0|0|0|0|0|0|0|0|0|0|0|0|0|0|0|25159|0|0|104|0|119406|0|36682|2574|0|0|0|660|0|0|0|0|0|0|0|29493|0|0|112598|0|0|52558|0|0|0|0|0|0|0|0|0|0|0|0|0|0|0|6473|0|0|0|0|0|0|0|0|70143|0|0|0|0|0|0|0|0|0|0|0|0|0|0|0|0|0|0|0|0|0|8267|0|3245</HistCounts>
      </HistItem>
    </Histograms>
    <Metadata>
      <MDI key="BandName">temperature_2m</MDI>
      <MDI key="SourceBandIndex">0</MDI>
      <MDI key="STATISTICS_COVARIANCES">1417.000867735701,2550.951276289828,3118.520549388491,4317.010402194273</MDI>
      <MDI key="STATISTICS_EXCLUDEDVALUES"></MDI>
      <MDI key="STATISTICS_MAXIMUM">131</MDI>
      <MDI key="STATISTICS_MEAN">24.935473012196</MDI>
      <MDI key="STATISTICS_MEDIAN">0.000000</MDI>
      <MDI key="STATISTICS_MINIMUM">0</MDI>
      <MDI key="STATISTICS_SKIPFACTORX">1</MDI>
      <MDI key="STATISTICS_SKIPFACTORY">1</MDI>
      <MDI key="STATISTICS_STDDEV">37.643071975275</MDI>
    </Metadata>
  </PAMRasterBand>
  <PAMRasterBand band="2">
    <Histograms>
      <HistItem>
        <HistMin>-0.5</HistMin>
        <HistMax>195.5</HistMax>
        <BucketCount>196</BucketCount>
        <IncludeOutOfRange>1</IncludeOutOfRange>
        <Approximate>0</Approximate>
        <HistCounts>988277|0|0|0|0|0|0|0|0|0|0|0|0|0|0|0|0|0|0|0|0|0|0|0|0|0|0|0|0|0|0|0|0|0|0|0|0|0|0|0|0|0|0|0|0|0|0|0|0|0|0|0|0|0|0|0|0|0|0|0|0|0|0|0|0|0|0|0|0|0|0|0|0|0|0|0|0|0|0|0|0|0|0|0|0|0|0|0|0|0|0|0|0|0|0|25159|0|0|0|0|0|0|0|0|0|0|104|0|0|0|119406|0|0|0|0|0|36682|0|0|0|0|2574|0|0|0|0|0|0|0|0|0|0|660|0|0|0|0|0|0|0|0|0|0|0|0|0|0|0|29493|0|0|0|0|112598|0|0|52558|0|0|0|0|0|0|0|0|0|0|0|0|0|0|0|0|0|0|0|6473|0|0|0|0|0|70143|0|0|0|0|0|0|0|0|0|0|0|8267|3245</HistCounts>
      </HistItem>
    </Histograms>
    <Metadata>
      <MDI key="BandName">temperature_2m</MDI>
      <MDI key="SourceBandIndex">0</MDI>
      <MDI key="STATISTICS_COVARIANCES">2550.951276289828,4624.430051715736,5682.77257896961,7864.357017761801</MDI>
      <MDI key="STATISTICS_EXCLUDEDVALUES"></MDI>
      <MDI key="STATISTICS_MAXIMUM">195</MDI>
      <MDI key="STATISTICS_MEAN">45.425292946948</MDI>
      <MDI key="STATISTICS_MEDIAN">0.000000</MDI>
      <MDI key="STATISTICS_MINIMUM">0</MDI>
      <MDI key="STATISTICS_SKIPFACTORX">1</MDI>
      <MDI key="STATISTICS_SKIPFACTORY">1</MDI>
      <MDI key="STATISTICS_STDDEV">68.003162071449</MDI>
    </Metadata>
  </PAMRasterBand>
  <PAMRasterBand band="3">
    <Histograms>
      <HistItem>
        <HistMin>-0.5</HistMin>
        <HistMax>193.5</HistMax>
        <BucketCount>194</BucketCount>
        <IncludeOutOfRange>1</IncludeOutOfRange>
        <Approximate>0</Approximate>
        <HistCounts>988277|0|0|0|0|0|0|0|0|0|0|0|0|0|0|0|0|0|0|0|0|0|0|0|0|0|0|0|0|0|0|0|0|0|0|0|0|0|0|0|0|0|0|0|0|0|0|0|0|0|0|0|0|0|0|0|0|0|0|0|0|0|0|0|0|0|0|0|0|0|0|0|0|0|0|0|0|0|0|0|0|0|0|0|0|0|0|0|0|0|0|0|0|0|0|0|0|0|0|0|0|0|0|0|0|0|0|0|0|0|0|0|0|0|0|0|0|0|0|0|0|0|0|0|0|0|0|0|0|0|0|0|0|0|0|0|0|0|0|0|0|0|0|0|0|0|0|0|0|0|0|0|0|0|0|0|0|0|0|0|0|0|25159|0|0|0|0|104|0|0|119406|0|0|36682|0|2574|0|0|0|0|0|660|0|0|0|0|0|29493|124110|52558|0|0|70143|6473</HistCounts>
      </HistItem>
    </Histograms>
    <Metadata>
      <MDI key="BandName">temperature_2m</MDI>
      <MDI key="SourceBandIndex">0</MDI>
      <MDI key="STATISTICS_COVARIANCES">3118.520549388491,5682.77257896961,7208.967759014163,10086.46522152925</MDI>
      <MDI key="STATISTICS_EXCLUDEDVALUES"></MDI>
      <MDI key="STATISTICS_MAXIMUM">193</MDI>
      <MDI key="STATISTICS_MEAN">58.260406598061</MDI>
      <MDI key="STATISTICS_MEDIAN">0.000000</MDI>
      <MDI key="STATISTICS_MINIMUM">0</MDI>
      <MDI key="STATISTICS_SKIPFACTORX">1</MDI>
      <MDI key="STATISTICS_SKIPFACTORY">1</MDI>
      <MDI key="STATISTICS_STDDEV">84.905640325094</MDI>
    </Metadata>
  </PAMRasterBand>
  <PAMRasterBand band="4">
    <ColorInterp>Alpha</ColorInterp>
    <Histograms>
      <HistItem>
        <HistMin>-0.5</HistMin>
        <HistMax>255.5</HistMax>
        <BucketCount>256</BucketCount>
        <IncludeOutOfRange>1</IncludeOutOfRange>
        <Approximate>0</Approximate>
        <HistCounts>988277|0|0|0|0|0|0|0|0|0|0|0|0|0|0|0|0|0|0|0|0|0|0|0|0|0|0|0|0|0|0|0|0|0|0|0|0|0|0|0|0|0|0|0|0|0|0|0|0|0|0|0|0|0|0|0|0|0|0|0|0|0|0|0|0|0|0|0|0|0|0|0|0|0|0|0|0|0|0|0|0|0|0|0|0|0|0|0|0|0|0|0|0|0|0|0|0|0|0|0|0|0|0|0|0|0|0|0|0|0|0|0|0|0|0|0|0|0|0|0|0|0|0|0|0|0|0|0|0|0|0|0|0|0|0|0|0|0|0|0|0|0|0|0|0|0|0|0|0|0|0|0|0|0|0|0|0|0|0|0|0|0|0|0|0|0|0|0|0|0|0|0|0|0|0|0|0|0|0|0|0|0|0|0|0|0|0|0|0|0|0|0|0|0|0|0|0|0|0|0|0|0|0|0|0|0|0|0|0|0|0|0|0|0|0|0|0|0|0|0|0|0|0|0|0|0|0|0|0|0|0|0|0|0|0|0|0|0|0|0|0|0|0|0|0|0|0|0|0|0|0|0|0|0|0|467362</HistCounts>
      </HistItem>
    </Histograms>
    <Metadata>
      <MDI key="BandName">temperature_2m</MDI>
      <MDI key="SourceBandIndex">0</MDI>
      <MDI key="STATISTICS_COVARIANCES">4317.010402194273,7864.357017761801,10086.46522152925,14174.42270098468</MDI>
      <MDI key="STATISTICS_EXCLUDEDVALUES"></MDI>
      <MDI key="STATISTICS_MAXIMUM">255</MDI>
      <MDI key="STATISTICS_MEAN">81.872847594767</MDI>
      <MDI key="STATISTICS_MEDIAN">0.000000</MDI>
      <MDI key="STATISTICS_MINIMUM">0</MDI>
      <MDI key="STATISTICS_SKIPFACTORX">1</MDI>
      <MDI key="STATISTICS_SKIPFACTORY">1</MDI>
      <MDI key="STATISTICS_STDDEV">119.05638454524</MDI>
    </Metadata>
  </PAMRasterBand>
</PAMDataset>
