<PAMDataset>
  <Metadata>
    <MDI key="DataType">Generic</MDI>
  </Metadata>
  <PAMRasterBand band="1">
    <Histograms>
      <HistItem>
        <HistMin>-0.5</HistMin>
        <HistMax>251.5</HistMax>
        <BucketCount>252</BucketCount>
        <IncludeOutOfRange>1</IncludeOutOfRange>
        <Approximate>0</Approximate>
        <HistCounts>64666|0|0|0|0|0|0|0|0|0|0|0|0|0|0|0|0|0|0|0|0|0|0|0|0|0|0|0|0|0|0|0|0|0|0|0|0|0|0|0|0|0|0|0|0|0|0|0|0|0|0|0|0|0|0|0|0|0|0|0|0|0|0|0|0|0|0|0|0|0|0|0|0|0|0|0|0|0|0|0|0|0|0|0|0|0|0|0|0|0|0|0|0|0|0|0|0|0|0|0|0|0|0|0|0|0|0|0|0|0|0|0|0|0|0|0|0|0|0|0|0|0|0|0|0|0|0|0|0|0|0|0|0|0|0|0|0|0|0|0|0|0|0|0|0|0|0|0|0|0|0|0|0|0|0|0|0|0|0|0|0|0|0|0|0|0|0|0|16|61|51|25|0|53|38|48|47|62|0|89|68|71|77|107|160|144|157|265|420|876|0|1401|1978|2601|2299|2258|2747|2291|2083|2313|2827|3564|10468|1720|1726|619|494|531|274|197|175|157|287|143|128|95|99|77|121|56|48|50|73|91|54|56|86|49|31|63|35|29|68|44|84|55|53|28|72|21|36|16|17|3|17|10|9|10|12|14|40|11</HistCounts>
      </HistItem>
    </Histograms>
    <Metadata>
      <MDI key="BandName">LST</MDI>
      <MDI key="SourceBandIndex">0</MDI>
      <MDI key="STATISTICS_COVARIANCES">9741.245149470717,3246.492798190022,6063.025615021589,12425.0050688089</MDI>
      <MDI key="STATISTICS_EXCLUDEDVALUES"></MDI>
      <MDI key="STATISTICS_MAXIMUM">251</MDI>
      <MDI key="STATISTICS_MEAN">84.778740612363</MDI>
      <MDI key="STATISTICS_MEDIAN">0.000000</MDI>
      <MDI key="STATISTICS_MINIMUM">0</MDI>
      <MDI key="STATISTICS_SKIPFACTORX">1</MDI>
      <MDI key="STATISTICS_SKIPFACTORY">1</MDI>
      <MDI key="STATISTICS_STDDEV">98.697746425492</MDI>
    </Metadata>
  </PAMRasterBand>
  <PAMRasterBand band="2">
    <Histograms>
      <HistItem>
        <HistMin>-0.5</HistMin>
        <HistMax>156.5</HistMax>
        <BucketCount>157</BucketCount>
        <IncludeOutOfRange>1</IncludeOutOfRange>
        <Approximate>0</Approximate>
        <HistCounts>64666|0|0|0|0|0|0|0|0|0|0|0|0|0|0|0|0|0|0|0|0|0|0|0|0|0|0|0|0|0|0|0|0|16|61|51|0|25|53|38|48|47|62|89|0|68|71|77|107|160|144|157|265|0|420|876|1401|1978|2601|2299|2258|0|2747|2291|2083|2313|2827|3564|6210|4258|0|1720|1726|619|494|531|274|197|0|175|157|131|156|143|128|95|0|99|77|62|59|56|48|50|0|73|43|48|54|56|50|0|36|49|31|28|35|0|35|29|40|28|44|0|46|38|55|21|0|32|28|38|34|0|21|27|9|8|0|8|7|10|0|3|7|10|2|0|8|6|3|0|7|3|10|0|2|0|0|9|5|10|0|12|18|0|11</HistCounts>
      </HistItem>
    </Histograms>
    <Metadata>
      <MDI key="BandName">LST</MDI>
      <MDI key="SourceBandIndex">0</MDI>
      <MDI key="STATISTICS_COVARIANCES">3246.492798190022,1107.95135321919,1977.273348017761,4107.34361459082</MDI>
      <MDI key="STATISTICS_EXCLUDEDVALUES"></MDI>
      <MDI key="STATISTICS_MAXIMUM">156</MDI>
      <MDI key="STATISTICS_MEAN">28.025374394526</MDI>
      <MDI key="STATISTICS_MEDIAN">0.000000</MDI>
      <MDI key="STATISTICS_MINIMUM">0</MDI>
      <MDI key="STATISTICS_SKIPFACTORX">1</MDI>
      <MDI key="STATISTICS_SKIPFACTORY">1</MDI>
      <MDI key="STATISTICS_STDDEV">33.285903220721</MDI>
    </Metadata>
  </PAMRasterBand>
  <PAMRasterBand band="3">
    <Histograms>
      <HistItem>
        <HistMin>-0.5</HistMin>
        <HistMax>152.5</HistMax>
        <BucketCount>153</BucketCount>
        <IncludeOutOfRange>1</IncludeOutOfRange>
        <Approximate>0</Approximate>
        <HistCounts>64666|0|0|0|0|0|0|0|0|0|0|0|0|0|0|0|0|0|0|0|0|0|0|0|0|0|0|0|0|0|0|0|0|0|0|0|0|0|0|0|0|0|0|0|0|0|0|0|0|0|0|0|0|0|0|0|0|0|0|0|0|11|18|12|15|9|0|2|10|3|10|6|8|2|10|7|3|17|8|8|9|27|21|72|28|32|21|55|38|46|72|40|29|35|35|28|80|36|50|56|54|48|116|50|48|56|59|62|77|194|128|143|156|131|157|175|197|805|494|619|1726|1720|4258|6210|3564|2827|2313|2083|2291|5005|2299|2601|1978|1401|876|420|265|157|144|160|107|77|71|68|89|109|48|38|53|25|51|61|16</HistCounts>
      </HistItem>
    </Histograms>
    <Metadata>
      <MDI key="BandName">LST</MDI>
      <MDI key="SourceBandIndex">0</MDI>
      <MDI key="STATISTICS_COVARIANCES">6063.025615021589,1977.273348017761,3847.462091130247,7790.959137005284</MDI>
      <MDI key="STATISTICS_EXCLUDEDVALUES"></MDI>
      <MDI key="STATISTICS_MAXIMUM">152</MDI>
      <MDI key="STATISTICS_MEAN">53.159552059725</MDI>
      <MDI key="STATISTICS_MEDIAN">0.000000</MDI>
      <MDI key="STATISTICS_MINIMUM">0</MDI>
      <MDI key="STATISTICS_SKIPFACTORX">1</MDI>
      <MDI key="STATISTICS_SKIPFACTORY">1</MDI>
      <MDI key="STATISTICS_STDDEV">62.027913806046</MDI>
    </Metadata>
  </PAMRasterBand>
  <PAMRasterBand band="4">
    <ColorInterp>Alpha</ColorInterp>
    <Histograms>
      <HistItem>
        <HistMin>-0.5</HistMin>
        <HistMax>255.5</HistMax>
        <BucketCount>256</BucketCount>
        <IncludeOutOfRange>1</IncludeOutOfRange>
        <Approximate>0</Approximate>
        <HistCounts>64666|0|0|0|0|0|0|0|0|0|0|0|0|0|0|0|0|0|0|0|0|0|0|0|0|0|0|0|0|0|0|0|0|0|0|0|0|0|0|0|0|0|0|0|0|0|0|0|0|0|0|0|0|0|0|0|0|0|0|0|0|0|0|0|0|0|0|0|0|0|0|0|0|0|0|0|0|0|0|0|0|0|0|0|0|0|0|0|0|0|0|0|0|0|0|0|0|0|0|0|0|0|0|0|0|0|0|0|0|0|0|0|0|0|0|0|0|0|0|0|0|0|0|0|0|0|0|0|0|0|0|0|0|0|0|0|0|0|0|0|0|0|0|0|0|0|0|0|0|0|0|0|0|0|0|0|0|0|0|0|0|0|0|0|0|0|0|0|0|0|0|0|0|0|0|0|0|0|0|0|0|0|0|0|0|0|0|0|0|0|0|0|0|0|0|0|0|0|0|0|0|0|0|0|0|0|0|0|0|0|0|0|0|0|0|0|0|0|0|0|0|0|0|0|0|0|0|0|0|0|0|0|0|0|0|0|0|0|0|0|0|0|0|0|0|0|0|0|0|0|0|0|0|0|0|47849</HistCounts>
      </HistItem>
    </Histograms>
    <Metadata>
      <MDI key="BandName">LST</MDI>
      <MDI key="SourceBandIndex">0</MDI>
      <MDI key="STATISTICS_COVARIANCES">12425.0050688089,4107.34361459082,7790.959137005284,15893.23245727424</MDI>
      <MDI key="STATISTICS_EXCLUDEDVALUES"></MDI>
      <MDI key="STATISTICS_MAXIMUM">255</MDI>
      <MDI key="STATISTICS_MEAN">108.4432742301</MDI>
      <MDI key="STATISTICS_MEDIAN">0.000000</MDI>
      <MDI key="STATISTICS_MINIMUM">0</MDI>
      <MDI key="STATISTICS_SKIPFACTORX">1</MDI>
      <MDI key="STATISTICS_SKIPFACTORY">1</MDI>
      <MDI key="STATISTICS_STDDEV">126.06836422066</MDI>
    </Metadata>
  </PAMRasterBand>
</PAMDataset>
